AUTHORS
COPYING
COPYING.LESSER
MANIFEST.in
README
TODO
ez_setup.py
setup.cfg
setup.py
doc/docking.gaphor
doc/examples/demo.py
doc/examples/demo.sav
doc/examples/dockgroupdemo.py
doc/examples/test.py
doc/platform/colors.html
doc/platform/colors.py
doc/reference/Makefile
doc/reference/conf.pyc
doc/reference/make.bat
doc/reference/source/conf.py
doc/reference/source/conf.pyc
doc/reference/source/index.rst
doc/reference/source/_static/.keep
doc/reference/source/_templates/.keep
doc/reference/source/api/dockframe.rst
doc/reference/source/api/dockgroup.rst
doc/reference/source/api/dockitem.rst
doc/reference/source/api/docklayout.rst
doc/reference/source/api/dockpaned.rst
doc/reference/source/dev/serialization.rst
lib/etk/__init__.py
lib/etk.docking.egg-info/PKG-INFO
lib/etk.docking.egg-info/SOURCES.txt
lib/etk.docking.egg-info/dependency_links.txt
lib/etk.docking.egg-info/namespace_packages.txt
lib/etk.docking.egg-info/not-zip-safe
lib/etk.docking.egg-info/requires.txt
lib/etk.docking.egg-info/top_level.txt
lib/etk/docking/__init__.py
lib/etk/docking/compactbutton.py
lib/etk/docking/dnd.py
lib/etk/docking/dockframe.py
lib/etk/docking/dockgroup.py
lib/etk/docking/dockitem.py
lib/etk/docking/docklayout.py
lib/etk/docking/dockpaned.py
lib/etk/docking/docksettings.py
lib/etk/docking/dockstore.py
lib/etk/docking/hslcolor.py
lib/etk/docking/util.py
lib/etk/docking/icons/16x16/compact-close-prelight.png
lib/etk/docking/icons/16x16/compact-close.png
lib/etk/docking/icons/16x16/compact-list.png
lib/etk/docking/icons/16x16/compact-maximize.png
lib/etk/docking/icons/16x16/compact-minimize.png
lib/etk/docking/icons/16x16/compact-restore.png