Metadata-Version: 1.0
Name: etk.docking
Version: 0.2
Summary: PyGTK Docking Widgets
Home-page: http://github.com/dieterv/etk.docking/
Author: etk.docking Contributors
Author-email: etk-list@googlegroups.com
License: GNU Lesser General Public License
Download-URL: http://github.com/dieterv/etk.docking/downloads/
Platform: UNKNOWN
Classifier: Development Status :: 4 - Beta
Classifier: Environment :: X11 Applications :: GTK
Classifier: Intended Audience :: Developers
Classifier: License :: OSI Approved :: GNU Library or Lesser General Public License (LGPL)
Classifier: Natural Language :: English
Classifier: Operating System :: MacOS :: MacOS X
Classifier: Operating System :: Microsoft :: Windows
Classifier: Operating System :: POSIX
Classifier: Programming Language :: Python
Classifier: Topic :: Software Development :: Libraries :: Python Modules
